utr/__init__.py
utr/utr.py
unntr-0.1.0.dist-info/METADATA
unntr-0.1.0.dist-info/WHEEL
unntr-0.1.0.dist-info/entry_points.txt
unntr-0.1.0.dist-info/top_level.txt
unntr-0.1.0.dist-info/RECORD
