Metadata-Version: 2.1
Name: unntr
Version: 0.1.0
Summary: A simple and small text replacement tool
Home-page: https://github.com/juanvel4000/uTR
Author: juanvel400
Classifier: Programming Language :: Python :: 3
Classifier: License :: OSI Approved :: MIT License
Requires-Python: >=3.6
